{
    "name": "AWS CLI",
    "version": "2.0.38",
    "archive": "AWS-CLI.tgz",
    "author": {
        "name": "Roberth Kulbin",
        "link": "https://github.com/roberth-k"
    },
    "aliases": [
        "aws",
        "aws-cli",
        "aws cli",
        "aws command line",
        "aws sdk"
    ],
    "specific_versions": [
        {
            "version": "2.0.38",
            "archive": "versions/2.0.38/AWS-CLI.tgz"
        },
        {
            "version": "2.0.37",
            "archive": "versions/2.0.37/AWS-CLI.tgz"
        },
        {
            "version": "2.0.36",
            "archive": "versions/2.0.36/AWS-CLI.tgz"
        },
        {
            "version": "2.0.35",
            "archive": "versions/2.0.35/AWS-CLI.tgz"
        },
        {
            "version": "2.0.34",
            "archive": "versions/2.0.34/AWS-CLI.tgz"
        },
        {
            "version": "2.0.29",
            "archive": "versions/2.0.29/AWS-CLI.tgz"
        }
    ]
}
