{
    "name": "Zimbra Zimlet API",
    "version": "8.7",
    "archive": "zimbra-js-api.tgz",
    "author": {
        "name": "Frederic Maussion",
        "link": "https://twitter.com/fred_maussion"
    },
    "aliases": [""],

    "specific_versions": [
        {
            "version": "8.7",
            "archive": "versions/8.7/zimbra-js-api.tgz",
        },
        {
            "version": "8.6",
            "archive": "versions/8.6/zimbra-js-api.tgz",
        },
        {
            "version": "8.5.1",
            "archive": "versions/8.5.1/zimbra-js-api.tgz",
        },
        {
            "version": "8.0.9",
            "archive": "versions/8.0.9/zimbra-js-api.tgz",
        },
        {
            "version": "8.0.7",
            "archive": "versions/8.0.7/zimbra-js-api.tgz",
        },
        {
            "version": "8.0.6",
            "archive": "versions/8.0.6/zimbra-js-api.tgz",
        },
        {
            "version": "8.0.5",
            "archive": "versions/8.0.5/zimbra-js-api.tgz",
        },
        {
            "version": "8.0.4",
            "archive": "versions/8.0.4/zimbra-js-api.tgz",
        },
        {
            "version": "8.0",
            "archive": "versions/8.0/zimbra-js-api.tgz",
        },
        {
            "version": "7.2.7",
            "archive": "versions/7.2.7/zimbra-js-api.tgz",
        },
        {
            "version": "7.2.4",
            "archive": "versions/7.2.4/zimbra-js-api.tgz",
        }
    ]
}
