{
    "name": "Amazon Redshift Database Developer Guide",
    "version": "2024.2.0",
    "archive": "versions/2024.2.0/redshift-en_US.tgz",
    "author": {
        "name": "tzing",
        "link": "https://github.com/tzing"
    },
    "aliases": [
        "amazon",
        "amazon web services",
        "aws",
        "redshift",
        "data warehouse",
        "sql"
    ],
    "specific_versions": [
        {
            "version": "2024.2.0-en_US",
            "archive": "versions/2024.2.0/redshift-en_US.tgz"
        },
        {
            "version": "2024.2.0-de_DE",
            "archive": "versions/2024.2.0/redshift-de_DE.tgz"
        },
        {
            "version": "2024.2.0-es_ES",
            "archive": "versions/2024.2.0/redshift-es_ES.tgz"
        },
        {
            "version": "2024.2.0-fr_FR",
            "archive": "versions/2024.2.0/redshift-fr_FR.tgz"
        },
        {
            "version": "2024.2.0-id_ID",
            "archive": "versions/2024.2.0/redshift-id_ID.tgz"
        },
        {
            "version": "2024.2.0-it_IT",
            "archive": "versions/2024.2.0/redshift-it_IT.tgz"
        },
        {
            "version": "2024.2.0-ja_JP",
            "archive": "versions/2024.2.0/redshift-ja_JP.tgz"
        },
        {
            "version": "2024.2.0-pt_BR",
            "archive": "versions/2024.2.0/redshift-pt_BR.tgz"
        },
        {
            "version": "2024.2.0-zh_CN",
            "archive": "versions/2024.2.0/redshift-zh_CN.tgz"
        },
        {
            "version": "2024.2.0-zh_TW",
            "archive": "versions/2024.2.0/redshift-zh_TW.tgz"
        },
        {
            "version": "2024.1.0",
            "archive": "versions/2024.1.0/redshift.tgz"
        },
        {
            "version": "2024.1.0-de_DE",
            "archive": "versions/2024.1.0/redshift-de_DE.tgz"
        },
        {
            "version": "2024.1.0-es_ES",
            "archive": "versions/2024.1.0/redshift-es_ES.tgz"
        },
        {
            "version": "2024.1.0-fr_FR",
            "archive": "versions/2024.1.0/redshift-fr_FR.tgz"
        },
        {
            "version": "2024.1.0-id_ID",
            "archive": "versions/2024.1.0/redshift-id_ID.tgz"
        },
        {
            "version": "2024.1.0-it_IT",
            "archive": "versions/2024.1.0/redshift-it_IT.tgz"
        },
        {
            "version": "2024.1.0-ja_JP",
            "archive": "versions/2024.1.0/redshift-ja_JP.tgz"
        },
        {
            "version": "2024.1.0-pt_BR",
            "archive": "versions/2024.1.0/redshift-pt_BR.tgz"
        },
        {
            "version": "2024.1.0-zh_CN",
            "archive": "versions/2024.1.0/redshift-zh_CN.tgz"
        },
        {
            "version": "2024.1.0-zh_TW",
            "archive": "versions/2024.1.0/redshift-zh_TW.tgz"
        }
    ]
}
